findata_market/__init__.py
findata_market/findata.py
findata_market-0.2.dist-info/LICENSE
findata_market-0.2.dist-info/METADATA
findata_market-0.2.dist-info/WHEEL
findata_market-0.2.dist-info/top_level.txt
findata_market-0.2.dist-info/RECORD
