Metadata-Version: 2.1
Name: findata_market
Version: 0.2
Summary: A simple package with findata function
Home-page: https://github.com/serkin/findata-market
Author: Serkin Alexander
Author-email: serkin.alexander@gmail.com
Classifier: Programming Language :: Python :: 3
Classifier: License :: OSI Approved :: MIT License
Classifier: Operating System :: OS Independent
Requires-Python: >=3.6
License-File: LICENSE
